covid19_cases/corona19.py
covid19_cases/test.py
covid19_cases-0.0.8.dist-info/LICENSE
covid19_cases-0.0.8.dist-info/METADATA
covid19_cases-0.0.8.dist-info/WHEEL
covid19_cases-0.0.8.dist-info/top_level.txt
covid19_cases-0.0.8.dist-info/RECORD
