Metadata-Version: 2.1
Name: covid19-cases
Version: 0.0.8
Summary: A Python Package to get covid19 Cases for any Country Real Time
Home-page: https://github.com/falahgs/
Author: Falahgs
Author-email: falahgs07@gmail.com
License: UNKNOWN
Platform: UNKNOWN
Classifier: Programming Language :: Python :: 3
Classifier: Programming Language :: Python :: 3.5
Classifier: Programming Language :: Python :: 3.6
Classifier: Programming Language :: Python :: 3.7
Classifier: Programming Language :: Python :: 3.8
Classifier: License :: OSI Approved :: MIT License
Classifier: Operating System :: OS Independent
Requires-Python: >=3.6
